README.md
setup.py
CharCore/__init__.py
CharCore/__log__.py
CharCore/_event.py
CharCore/_window.py
CharCore.egg-info/PKG-INFO
CharCore.egg-info/SOURCES.txt
CharCore.egg-info/dependency_links.txt
CharCore.egg-info/requires.txt
CharCore.egg-info/top_level.txt
CharCore/_scene/__init__.py
CharCore/_scene/__log__.py
CharCore/_scene/_meta.py
CharCore/_scene/camera.py
CharCore/_scene/scene.py
CharCore/_scene/screen.py
CharCore/_scene/_delegate/__init__.py
CharCore/_scene/_delegate/base_delegate.py
CharCore/_scene/_delegate/batch_delegate.py
CharCore/_scene/_delegate/element_delegate.py
CharCore/_scene/_delegate/entity_delegate.py
CharCore/_scene/_delegate/label_delegate.py